LICENSE.txt
MANIFEST.in
README.md
setup.cfg
setup.py
alpha_vantage/__init__.py
alpha_vantage/alphavantage.py
alpha_vantage/cryptocurrencies.py
alpha_vantage/foreignexchange.py
alpha_vantage/fundamentaldata.py
alpha_vantage/sectorperformance.py
alpha_vantage/techindicators.py
alpha_vantage/timeseries.py
alpha_vantage/async_support/__init__.py
alpha_vantage/async_support/alphavantage.py
alpha_vantage/async_support/cryptocurrencies.py
alpha_vantage/async_support/foreignexchange.py
alpha_vantage/async_support/sectorperformance.py
alpha_vantage/async_support/techindicators.py
alpha_vantage/async_support/timeseries.py
alpha_vantage_atarax.egg-info/PKG-INFO
alpha_vantage_atarax.egg-info/SOURCES.txt
alpha_vantage_atarax.egg-info/dependency_links.txt
alpha_vantage_atarax.egg-info/requires.txt
alpha_vantage_atarax.egg-info/top_level.txt