Metadata-Version: 2.1
Name: alpha-vantage-atarax
Version: 2.3.1
Summary: Python module to get stock data from the Alpha Vantage Api
Home-page: https://github.com/atarax/alpha_vantage_atarax
Author: Romel J. Torres
Author-email: romel.torres@gmail.com
License: MIT
Keywords: stocks,market,finance,alpha_vantage,quotes,shares
Platform: UNKNOWN
Classifier: Development Status :: 5 - Production/Stable
Classifier: Intended Audience :: Developers
Classifier: Topic :: Office/Business :: Financial :: Investment
Classifier: License :: OSI Approved :: MIT License
Classifier: Programming Language :: Python :: 2.7
Classifier: Programming Language :: Python :: 3.4
Classifier: Programming Language :: Python :: 3.5
Classifier: Programming Language :: Python :: 3.6
Classifier: Programming Language :: Python :: 3.7
Classifier: Programming Language :: Python :: 3.8
